faktotum/__init__.py
faktotum/kb.py
faktotum/models.py
faktotum/pipelines.py
faktotum/research/__init__.py
faktotum/research/classification.py
faktotum/research/clustering/__init__.py
faktotum/research/clustering/droc.py
faktotum/research/clustering/smartdata.py
faktotum/research/clustering/utils.py
faktotum/research/corpus/__init__.py
faktotum/research/corpus/api.py
faktotum/research/corpus/core.py
faktotum/research/e2e_eval.py
faktotum/research/evaluation.py
faktotum/research/exploration/__init__.py
faktotum/research/exploration/evaluation.py
faktotum/research/exploration/lda.py
faktotum/research/exploration/similarities.py
faktotum/research/knowledge/__init__.py
faktotum/research/knowledge/utils.py
faktotum/research/knowledge/wikidata.py
faktotum/research/linking/__init__.py
faktotum/research/linking/droc.py
faktotum/research/linking/smartdata.py
faktotum/research/modeling/__init__.py
faktotum/research/modeling/bert.py
faktotum/research/ner.py
faktotum/research/ontologia/__init__.py
faktotum/research/ontologia/models.py
faktotum/research/ontologia/rules.py
faktotum/research/regression.py
faktotum/research/similarity.py
faktotum/research/utils.py
faktotum/research/vendor/__init__.py
faktotum/research/vendor/droc/entities.json
faktotum/research/vendor/droc/test.txt
faktotum/research/vendor/droc/train.txt
faktotum/research/vendor/lm.py
faktotum/research/vendor/ner.py
faktotum/research/vendor/smartdata/entities.json
faktotum/research/vendor/smartdata/test.txt
faktotum/research/vendor/smartdata/train.txt
faktotum/research/vendor/utils_ner.py
faktotum/typing.py
faktotum/utils.py
faktotum-1.0.0.dist-info/LICENSE
faktotum-1.0.0.dist-info/WHEEL
faktotum-1.0.0.dist-info/METADATA
faktotum-1.0.0.dist-info/RECORD
